aind_behavior_core_analysis/__init__.py
aind_behavior_core_analysis/_typing.py
aind_behavior_core_analysis/py.typed
aind_behavior_core_analysis/contract/__init__.py
aind_behavior_core_analysis/contract/base.py
aind_behavior_core_analysis/contract/camera.py
aind_behavior_core_analysis/contract/csv.py
aind_behavior_core_analysis/contract/harp.py
aind_behavior_core_analysis/contract/json.py
aind_behavior_core_analysis/contract/mux.py
aind_behavior_core_analysis/contract/text.py
aind_behavior_core_analysis/contract/utils.py
aind_behavior_core_analysis/qc/__init__.py
aind_behavior_core_analysis/qc/_context_extensions.py
aind_behavior_core_analysis/qc/base.py
aind_behavior_core_analysis/qc/camera.py
aind_behavior_core_analysis/qc/contract.py
aind_behavior_core_analysis/qc/csv.py
aind_behavior_core_analysis/qc/harp.py
aind_behavior_core_analysis-0.2.1.dist-info/licenses/LICENSE
aind_behavior_core_analysis-0.2.1.dist-info/METADATA
aind_behavior_core_analysis-0.2.1.dist-info/WHEEL
aind_behavior_core_analysis-0.2.1.dist-info/top_level.txt
aind_behavior_core_analysis-0.2.1.dist-info/RECORD
