Metadata-Version: 2.4
Name: aind-behavior-core-analysis
Version: 0.2.1
Summary: A library with core primitives for analysis shared across all `Aind.Behavior` tasks
Author-email: Bruno Cruz <bruno.cruz@alleninstitute.org>
License-Expression: MIT
Project-URL: Documentation, https://allenneuraldynamics.github.io/Aind.Behavior.CoreAnalysis/
Project-URL: Repository, https://github.com/AllenNeuralDynamics/Aind.Behavior.CoreAnalysis/
Project-URL: Issues, https://github.com/AllenNeuralDynamics/Aind.Behavior.CoreAnalysis/issues
Project-URL: Changelog, https://github.com/AllenNeuralDynamics/Aind.Behavior.CoreAnalysis/releases
Classifier: Programming Language :: Python :: 3.11
Classifier: Operating System :: Microsoft :: Windows
Requires-Python: >=3.11
License-File: LICENSE
Requires-Dist: aind_behavior_services
Requires-Dist: harp-python
Requires-Dist: matplotlib
Requires-Dist: numpy
Requires-Dist: pandas
Requires-Dist: pydantic
Requires-Dist: pyyaml
Requires-Dist: requests
Requires-Dist: rich
Requires-Dist: semver
Requires-Dist: opencv-python
Provides-Extra: dev
Requires-Dist: codespell; extra == "dev"
Requires-Dist: pytest; extra == "dev"
Requires-Dist: pytest-cov; extra == "dev"
Requires-Dist: ruff; extra == "dev"
Requires-Dist: interrogate; extra == "dev"
Provides-Extra: docs
Requires-Dist: mkdocs; extra == "docs"
Requires-Dist: mkdocs-material; extra == "docs"
Requires-Dist: mkdocstrings[python]; extra == "docs"
Requires-Dist: pymdown-extensions; extra == "docs"
Requires-Dist: ruff; extra == "docs"
Dynamic: license-file
